OCDocker/Config.py
OCDocker/Error.py
OCDocker/Initialise.py
OCDocker/Ligand.py
OCDocker/Receptor.py
OCDocker/__init__.py
OCDocker/CLI/__init__.py
OCDocker/DB/DB.py
OCDocker/DB/DBMinimal.py
OCDocker/DB/DUDEz.py
OCDocker/DB/PDBbind.py
OCDocker/DB/__init__.py
OCDocker/DB/baseDB.py
OCDocker/DB/Models/Base.py
OCDocker/DB/Models/Complexes.py
OCDocker/DB/Models/Ligands.py
OCDocker/DB/Models/Receptors.py
OCDocker/DB/Models/__init__.py
OCDocker/Docking/BaseVinaLike.py
OCDocker/Docking/PLANTS.py
OCDocker/Docking/Smina.py
OCDocker/Docking/Vina.py
OCDocker/Docking/__init__.py
OCDocker/Docking/Future/Dock3.py
OCDocker/Docking/Future/Dock6.py
OCDocker/Docking/Future/GEMDOCK.py
OCDocker/Docking/Future/Gnina.py
OCDocker/Docking/Future/Ledock.py
OCDocker/Docking/Future/RDock.py
OCDocker/Docking/Future/__init__.py
OCDocker/OCScore/Scoring.py
OCDocker/OCScore/__init__.py
OCDocker/OCScore/Analysis/Correlation.py
OCDocker/OCScore/Analysis/FeatureImportance.py
OCDocker/OCScore/Analysis/Impact.py
OCDocker/OCScore/Analysis/NNUtils.py
OCDocker/OCScore/Analysis/PerformanceEvaluation.py
OCDocker/OCScore/Analysis/RankingMetrics.py
OCDocker/OCScore/Analysis/StatTests.py
OCDocker/OCScore/Analysis/StudyProcessing.py
OCDocker/OCScore/Analysis/__init__.py
OCDocker/OCScore/Analysis/Metrics/Bootstrap.py
OCDocker/OCScore/Analysis/Metrics/Ranking.py
OCDocker/OCScore/Analysis/Metrics/__init__.py
OCDocker/OCScore/Analysis/Plotting/Colouring.py
OCDocker/OCScore/Analysis/Plotting/Core.py
OCDocker/OCScore/Analysis/Plotting/ImpactPlots.py
OCDocker/OCScore/Analysis/Plotting/MetricsPlots.py
OCDocker/OCScore/Analysis/Plotting/Stats.py
OCDocker/OCScore/Analysis/Plotting/__init__.py
OCDocker/OCScore/Analysis/SHAP/Cli.py
OCDocker/OCScore/Analysis/SHAP/Data.py
OCDocker/OCScore/Analysis/SHAP/Explain.py
OCDocker/OCScore/Analysis/SHAP/Model.py
OCDocker/OCScore/Analysis/SHAP/Plots.py
OCDocker/OCScore/Analysis/SHAP/Runner.py
OCDocker/OCScore/Analysis/SHAP/Studies.py
OCDocker/OCScore/Analysis/SHAP/__init__.py
ocdocker-0.11.1.dist-info/licenses/LICENSE
ocdocker-0.11.1.dist-info/METADATA
ocdocker-0.11.1.dist-info/WHEEL
ocdocker-0.11.1.dist-info/entry_points.txt
ocdocker-0.11.1.dist-info/top_level.txt
ocdocker-0.11.1.dist-info/RECORD
