Metadata-Version: 2.4
Name: OCDocker
Version: 0.11.1
Summary: OCDocker is a Python package for molecular docking automation, virtual screening and AI consensus scoring.
Author-email: Artur Duque Rossi <arturossi10@gmail.com>
License: This computer program is owned by the Federal University of Rio de Janeiro (UFRJ), developed by Artur Duque Rossi and Pedro Henrique Monteiro Torres, and protected under the Brazilian Law No. 9,609/1998.
Project-URL: Homepage, https://github.com/Arturossi/OCDocker
Project-URL: Repository, https://github.com/Arturossi/OCDocker
Project-URL: Issues, https://github.com/Arturossi/OCDocker/issues
Keywords: docking,virtual screening,AI,bioinformatics,drug discovery
Classifier: Programming Language :: Python :: 3
Classifier: License :: OSI Approved :: Apache Software License
Classifier: Operating System :: POSIX :: Linux
Classifier: Development Status :: 4 - Beta
Classifier: Intended Audience :: Science/Research
Classifier: Topic :: Scientific/Engineering :: Bio-Informatics
Requires-Python: >=3.11
License-File: LICENSE
Requires-Dist: numpy>=1.26.4
Requires-Dist: pandas>=2.2.3
Requires-Dist: scipy>=1.14.1
Requires-Dist: scikit-learn>=1.5.2
Requires-Dist: scikit-image>=0.24.0
Requires-Dist: torch>=2.4.1
Requires-Dist: torchaudio>=2.4.1
Requires-Dist: torchvision>=0.19.1
Requires-Dist: xgboost>=2.1.1
Requires-Dist: optuna>=3.6.1
Requires-Dist: rdkit>=2024.09.1
Requires-Dist: openbabel>=3.1.1
Requires-Dist: biopython>=1.84
Requires-Dist: spyrmsd>=0.8.0
Requires-Dist: seaborn>=0.13.2
Requires-Dist: matplotlib>=3.9.2
Requires-Dist: pingouin>=0.5.5
Requires-Dist: statsmodels>=0.14.3
Requires-Dist: torchsummary
Requires-Dist: torchviz
Requires-Dist: visualtorch>=0.2.3
Requires-Dist: pyyaml>=6.0.2
Requires-Dist: joblib>=1.4.2
Requires-Dist: dcor>=0.6
Requires-Dist: fsspec>=2024.10.0
Requires-Dist: numba>=0.60.0
Requires-Dist: graphviz>=0.20.3
Requires-Dist: lime>=0.2.0.1
Requires-Dist: networkx>=3.3
Requires-Dist: rustworkx>=0.15.1
Requires-Dist: sqlalchemy>=2.0.35
Requires-Dist: sqlalchemy-utils>=0.41.2
Requires-Dist: pymysql>=1.1.1
Requires-Dist: configargparse>=1.7
Requires-Dist: python-dotenv>=1.1.0
Requires-Dist: requests>=2.32.3
Requires-Dist: aiohttp>=3.10.8
Requires-Dist: tqdm>=4.66.5
Requires-Dist: rich>=13.9.1
Requires-Dist: typer>=0.15.3
Requires-Dist: click>=8.2.1
Requires-Dist: colorlog>=6.8.2
Requires-Dist: h5py>=3.11.0
Requires-Dist: tifffile>=2024.9.20
Requires-Dist: imageio>=2.35.1
Requires-Dist: pillow>=10.4.0
Requires-Dist: python-dateutil>=2.9.0
Requires-Dist: pytz>=2024.1
Requires-Dist: six>=1.17.0
Requires-Dist: pydantic>=2.11.4
Requires-Dist: pydantic-settings>=2.9.1
Requires-Dist: jsonschema>=4.23.0
Requires-Dist: pyparsing>=3.1.4
Requires-Dist: attrs>=24.2.0
Requires-Dist: certifi>=2025.4.26
Requires-Dist: urllib3>=2.2.3
Requires-Dist: charset-normalizer>=3.3.2
Requires-Dist: idna>=3.10
Requires-Dist: ipython>=8.28.0
Requires-Dist: sympy>=1.13.3
Requires-Dist: mpmath>=1.3.0
Requires-Dist: gmpy2>=2.1.5
Requires-Dist: llvmlite>=0.43.0
Requires-Dist: packaging>=25.0
Provides-Extra: dev
Requires-Dist: pytest>=8.3.3; extra == "dev"
Requires-Dist: pytest-cov>=6.1.1; extra == "dev"
Requires-Dist: pytest-order>=1.3.0; extra == "dev"
Requires-Dist: coverage>=7.8.1; extra == "dev"
Requires-Dist: mypy>=1.0.0; extra == "dev"
Provides-Extra: docs
Requires-Dist: sphinx>=8.2.3; extra == "docs"
Requires-Dist: furo; extra == "docs"
Requires-Dist: sphinx-argparse>=0.5.2; extra == "docs"
Requires-Dist: sphinx-rtd-theme>=3.0.2; extra == "docs"
Requires-Dist: myst-parser>=4.0.1; extra == "docs"
Provides-Extra: cloud
Requires-Dist: boto3>=1.35.31; extra == "cloud"
Requires-Dist: google-cloud-storage>=2.18.2; extra == "cloud"
Requires-Dist: dropbox>=12.0.2; extra == "cloud"
Provides-Extra: workflow
Requires-Dist: snakemake>=7.32.4; extra == "workflow"
Provides-Extra: build
Requires-Dist: setuptools>=80.8.0; extra == "build"
Requires-Dist: wheel>=0.44.0; extra == "build"
Requires-Dist: build>=1.2.2.post1; extra == "build"
Requires-Dist: twine>=6.1.0; extra == "build"
Dynamic: license-file
